EVsSimulator/__init__.py
EVsSimulator/ev_city.py
EVsSimulator/baselines/__init__.py
EVsSimulator/baselines/heuristics.py
EVsSimulator/baselines/DDPG/__init__.py
EVsSimulator/baselines/DDPG/ddpg.py
EVsSimulator/baselines/DDPG/nets.py
EVsSimulator/baselines/DDPG/noise.py
EVsSimulator/baselines/DDPG/replay_memory.py
EVsSimulator/baselines/DT/__init__.py
EVsSimulator/baselines/gurobi_models/__init__.py
EVsSimulator/baselines/gurobi_models/profit_max.py
EVsSimulator/baselines/gurobi_models/tracking_error.py
EVsSimulator/data/Netherlands_day-ahead-2015-2023.csv
EVsSimulator/data/__init__.py
EVsSimulator/data/development-in-power-dem.csv
EVsSimulator/data/distribution-of-arrival-weekend.csv
EVsSimulator/data/distribution-of-arrival.csv
EVsSimulator/data/distribution-of-charging.csv
EVsSimulator/data/distribution-of-connection-time.csv
EVsSimulator/data/distribution-of-energy-demand.csv
EVsSimulator/data/eda_day-ahead_prices.py
EVsSimulator/data/elaad_data_eda.py
EVsSimulator/data/ev_specs.json
EVsSimulator/data/loads_eda.py
EVsSimulator/data/mean-demand-per-arrival.csv
EVsSimulator/data/mean-session-length-per.csv
EVsSimulator/data/pv_netherlands.csv
EVsSimulator/data/residential_loads.csv
EVsSimulator/data/time_of_connection_vs_hour.npy
EVsSimulator/example_config_files/BusinessPST.yaml
EVsSimulator/example_config_files/PublicPST.yaml
EVsSimulator/example_config_files/V2GProfitMax.yaml
EVsSimulator/example_config_files/V2GProfitPlusLoads.yaml
EVsSimulator/example_config_files/V2G_MPC.yaml
EVsSimulator/example_config_files/__init__.py
EVsSimulator/example_config_files/charging_topology_10.json
EVsSimulator/models/__init__.py
EVsSimulator/models/ev.py
EVsSimulator/models/ev_charger.py
EVsSimulator/models/grid.py
EVsSimulator/models/replay.py
EVsSimulator/models/transformer.py
EVsSimulator/rl_agent/__init__.py
EVsSimulator/rl_agent/reward.py
EVsSimulator/rl_agent/state.py
EVsSimulator/utilities/__init__.py
EVsSimulator/utilities/arg_parser.py
EVsSimulator-0.0.12.dist-info/LICENSE
EVsSimulator-0.0.12.dist-info/METADATA
EVsSimulator-0.0.12.dist-info/WHEEL
EVsSimulator-0.0.12.dist-info/top_level.txt
EVsSimulator-0.0.12.dist-info/RECORD
