Metadata-Version: 2.1
Name: EVsSimulator
Version: 0.0.12
Summary: A realistic V2X environment using gym
Author: Stavros Orfanoudakis
Keywords: gym,Reinforcement Learning,V2X,EVs,EVsSimulator,Electric Vehicles,Electric Vehicle Simulator
Classifier: Programming Language :: Python :: 3
Classifier: License :: OSI Approved :: MIT License
Classifier: Operating System :: OS Independent
Requires-Python: >=3.6
License-File: LICENSE
Requires-Dist: gymnasium
Requires-Dist: pyyaml
Requires-Dist: matplotlib
Requires-Dist: pandas
Requires-Dist: networkx
Requires-Dist: gurobipy
